{
    "Orders": [
        {
            "Value": "Damselfly",
            "Name": "豆娘",
            "Subitems": [
                {
                    "Value": "Calopterygidae",
                    "Name": "珈蟌科",
                    "Subitems": [
                        {
                            "Value": "01",
                            "Name": "白痣珈蟌"
                        },
                        {
                            "Value": "02",
                            "Name": "細胸珈蟌"
                        },
                        {
                            "Value": "03",
                            "Name": "綠翅珈蟌"
                        },
                        {
                            "Value": "04",
                            "Name": "中華珈蟌南臺亞種"
                        },
                        {
                            "Value": "05",
                            "Name": "中華珈蟌指名亞種"
                        }
                    ]
                },
                {
                    "Value": "Chlorocyphidae",
                    "Name": "鼓蟌科",
                    "Subitems": [
                        {
                            "Value": "01",
                            "Name": "脊紋鼓蟌"
                        },
                        {
                            "Value": "02",
                            "Name": "簾格鼓蟌"
                        },
                        {
                            "Value": "03",
                            "Name": "棋紋鼓蟌"
                        },
                        {
                            "Value": "04",
                            "Name": "朱環鼓蟌"
                        }
                    ]
                },
                {
                    "Value": "Coenagrionidae",
                    "Name": "細蟌科",
                    "Subitems": [
                        {
                            "Value": "01",
                            "Name": "針尾細蟌"
                        },
                        {
                            "Value": "02",
                            "Name": "白粉細蟌"
                        },
                        {
                            "Value": "03",
                            "Name": "橙尾細蟌"
                        },
                        {
                            "Value": "04",
                            "Name": "紅腹細蟌"
                        },
                        {
                            "Value": "05",
                            "Name": "昧影細蟌"
                        },
                        {
                            "Value": "06",
                            "Name": "黃腹細蟌"
                        },
                        {
                            "Value": "07",
                            "Name": "朱紅細蟌"
                        },
                        {
                            "Value": "08",
                            "Name": "亞東細蟌"
                        },
                        {
                            "Value": "09",
                            "Name": "朝雲細蟌"
                        },
                        {
                            "Value": "10",
                            "Name": "青紋細蟌"
                        },
                        {
                            "Value": "11",
                            "Name": "四斑細蟌"
                        },
                        {
                            "Value": "12",
                            "Name": "月斑細蟌"
                        },
                        {
                            "Value": "13",
                            "Name": "藍彩細蟌"
                        },
                        {
                            "Value": "14",
                            "Name": "葦笛細蟌"
                        },
                        {
                            "Value": "15",
                            "Name": "蔚藍細蟌"
                        },
                        {
                            "Value": "16",
                            "Name": "錢博細蟌"
                        },
                        {
                            "Value": "17",
                            "Name": "瘦面細蟌"
                        },
                        {
                            "Value": "18",
                            "Name": "弓背細蟌"
                        },
                        {
                            "Value": "19",
                            "Name": "丹頂細蟌"
                        }
                    ]
                },
                {
                    "Value": "Euphaeidae",
                    "Name": "幽蟌科",
                    "Subitems": [
                        {
                            "Value": "01",
                            "Name": "短尾幽蟌"
                        },
                        {
                            "Value": "02",
                            "Name": "短腹幽蟌"
                        }
                    ]
                },
                {
                    "Value": "Lestidae",
                    "Name": "絲蟌科",
                    "Subitems": [
                        {
                            "Value": "01",
                            "Name": "青紋絲蟌"
                        },
                        {
                            "Value": "02",
                            "Name": "鑲紋絲蟌"
                        },
                        {
                            "Value": "03",
                            "Name": "隱紋絲蟌"
                        },
                        {
                            "Value": "04",
                            "Name": "長痣絲蟌"
                        }
                    ]
                },
                {
                    "Value": "Megapodagrionidae",
                    "Name": "蹣蟌科",
                    "Subitems": [
                        {
                            "Value": "01",
                            "Name": "芽痣蹣蟌"
                        }
                    ]
                },
                {
                    "Value": "Platycnemididae",
                    "Name": "琵蟌科",
                    "Subitems": [
                        {
                            "Value": "01",
                            "Name": "美姿琵蟌"
                        },
                        {
                            "Value": "02",
                            "Name": "青黑琵蟌"
                        },
                        {
                            "Value": "03",
                            "Name": "青黑琵蟌"
                        },
                        {
                            "Value": "04",
                            "Name": "環紋琵蟌"
                        },
                        {
                            "Value": "05",
                            "Name": "脛蹼琵蟌"
                        }
                    ]
                },
                {
                    "Value": "Protoneuridae",
                    "Name": "樸蟌科",
                    "Subitems": [
                        {
                            "Value": "01",
                            "Name": "朱背樸蟌"
                        },
                        {
                            "Value": "02",
                            "Name": "烏齒樸蟌"
                        }
                    ]
                },
                {
                    "Value": "Synlestidae",
                    "Name": "洵蟌科",
                    "Subitems": [
                        {
                            "Value": "01",
                            "Name": "黃腹洵蟌"
                        },
                        {
                            "Value": "02",
                            "Name": "黃肩洵蟌"
                        }
                    ]
                }
            ]
        },
        {
            "Value": "Dragonfly",
            "Name": "蜻蜓",
            "Subitems": [
                {
                    "Value": "Aeshnidae",
                    "Name": "晏蜓科",
                    "Subitems": [
                        {
                            "Value": "01",
                            "Name": "泰雅晏蜓"
                        },
                        {
                            "Value": "02",
                            "Name": "碧翠晏蜓"
                        },
                        {
                            "Value": "03",
                            "Name": "烏基晏蜓"
                        },
                        {
                            "Value": "04",
                            "Name": "烏點晏蜓"
                        },
                        {
                            "Value": "05",
                            "Name": "烏帶晏蜓"
                        },
                        {
                            "Value": "06",
                            "Name": "麻斑晏蜓"
                        },
                        {
                            "Value": "07",
                            "Name": "綠胸晏蜓"
                        },
                        {
                            "Value": "08",
                            "Name": "微刺晏蜓"
                        },
                        {
                            "Value": "09",
                            "Name": "浡鋏晏蜓"
                        },
                        {
                            "Value": "10",
                            "Name": "長鋏晏蜓"
                        },
                        {
                            "Value": "11",
                            "Name": "倭鋏晏蜓"
                        },
                        {
                            "Value": "12",
                            "Name": "琉球晏蜓"
                        },
                        {
                            "Value": "13",
                            "Name": "舞鋏晏蜓"
                        },
                        {
                            "Value": "14",
                            "Name": "柱鋏晏蜓"
                        },
                        {
                            "Value": "15",
                            "Name": "石垣晏蜓"
                        },
                        {
                            "Value": "16",
                            "Name": "李斯晏蜓"
                        },
                        {
                            "Value": "17",
                            "Name": "陽明晏蜓"
                        },
                        {
                            "Value": "18",
                            "Name": "朱黛晏蜓"
                        },
                        {
                            "Value": "19",
                            "Name": "描金晏蜓"
                        },
                        {
                            "Value": "20",
                            "Name": "喙鋏晏蜓"
                        },
                        {
                            "Value": "21",
                            "Name": "日清晏蜓"
                        },
                        {
                            "Value": "22",
                            "Name": "源埡晏蜓"
                        },
                        {
                            "Value": "23",
                            "Name": "刃鋏晏蜓"
                        },
                        {
                            "Value": "24",
                            "Name": "鉤鋏晏蜓"
                        },
                        {
                            "Value": "25",
                            "Name": "短鋏晏蜓"
                        }
                    ]
                },
                {
                    "Value": "Cordulegastridae",
                    "Name": "勾蜓科",
                    "Subitems": [
                        {
                            "Value": "01",
                            "Name": "無霸勾蜓"
                        },
                        {
                            "Value": "02",
                            "Name": "短痣勾蜓"
                        },
                        {
                            "Value": "03",
                            "Name": "褐翼勾蜓"
                        },
                        {
                            "Value": "04",
                            "Name": "闊翼勾蜓"
                        },
                        {
                            "Value": "05",
                            "Name": "斑翼勾蜓"
                        }
                    ]
                },
                {
                    "Value": "Corduliidae",
                    "Name": "弓蜓科",
                    "Subitems": [
                        {
                            "Value": "01",
                            "Name": "慧眼弓蜓"
                        },
                        {
                            "Value": "02",
                            "Name": "岷峨弓蜓"
                        },
                        {
                            "Value": "03",
                            "Name": "褐面弓蜓"
                        },
                        {
                            "Value": "04",
                            "Name": "海神弓蜓"
                        },
                        {
                            "Value": "05",
                            "Name": "耀沂弓蜓"
                        },
                        {
                            "Value": "06",
                            "Name": "天王弓蜓"
                        },
                        {
                            "Value": "07",
                            "Name": "黃尾弓蜓"
                        },
                        {
                            "Value": "08",
                            "Name": "臺灣弓蜓"
                        }
                    ]
                },
                {
                    "Value": "Gomphidae",
                    "Name": "春蜓科",
                    "Subitems": [
                        {
                            "Value": "01",
                            "Name": "國姓春蜓"
                        },
                        {
                            "Value": "02",
                            "Name": "長唇春蜓"
                        },
                        {
                            "Value": "03",
                            "Name": "海南春蜓"
                        },
                        {
                            "Value": "04",
                            "Name": "雙角春蜓"
                        },
                        {
                            "Value": "05",
                            "Name": "圓痣春蜓"
                        },
                        {
                            "Value": "06",
                            "Name": "鉤紋春蜓"
                        },
                        {
                            "Value": "07",
                            "Name": "蟲莖春蜓"
                        },
                        {
                            "Value": "08",
                            "Name": "火神春蜓"
                        },
                        {
                            "Value": "09",
                            "Name": "聯紋春蜓"
                        },
                        {
                            "Value": "10",
                            "Name": "異紋春蜓"
                        },
                        {
                            "Value": "11",
                            "Name": "曲尾春蜓"
                        },
                        {
                            "Value": "12",
                            "Name": "粗鉤春蜓"
                        },
                        {
                            "Value": "13",
                            "Name": "鉤尾春蜓"
                        },
                        {
                            "Value": "14",
                            "Name": "紹德春蜓指名亞種"
                        },
                        {
                            "Value": "15",
                            "Name": "紹德春蜓嘉義亞種"
                        },
                        {
                            "Value": "16",
                            "Name": "窄胸春蜓"
                        },
                        {
                            "Value": "17",
                            "Name": "闊腹春蜓"
                        },
                        {
                            "Value": "18",
                            "Name": "細鉤春蜓"
                        },
                        {
                            "Value": "19",
                            "Name": "鉸剪春蜓"
                        },
                        {
                            "Value": "20",
                            "Name": "球角春蜓"
                        },
                        {
                            "Value": "21",
                            "Name": "錘角春蜓"
                        },
                        {
                            "Value": "22",
                            "Name": "南山春蜓"
                        }
                    ]
                },
                {
                    "Value": "Libellulidae",
                    "Name": "蜻蜓科",
                    "Subitems": [
                        {
                            "Value": "01",
                            "Name": "粗腰蜻蜓"
                        },
                        {
                            "Value": "02",
                            "Name": "八仙蜻蜓"
                        },
                        {
                            "Value": "03",
                            "Name": "橙斑蜻蜓"
                        },
                        {
                            "Value": "04",
                            "Name": "褐斑蜻蜓"
                        },
                        {
                            "Value": "05",
                            "Name": "線紋蜻蜓"
                        },
                        {
                            "Value": "06",
                            "Name": "猩紅蜻蜓"
                        },
                        {
                            "Value": "07",
                            "Name": "短痣蜻蜓"
                        },
                        {
                            "Value": "08",
                            "Name": "侏儒蜻蜓"
                        },
                        {
                            "Value": "09",
                            "Name": "硃紅蜻蜓"
                        },
                        {
                            "Value": "10",
                            "Name": "海神蜻蜓"
                        },
                        {
                            "Value": "11",
                            "Name": "廣腹蜻蜓"
                        },
                        {
                            "Value": "12",
                            "Name": "樹穴蜻蜓"
                        },
                        {
                            "Value": "13",
                            "Name": "高翔蜻蜓"
                        },
                        {
                            "Value": "14",
                            "Name": "小紅蜻蜓"
                        },
                        {
                            "Value": "15",
                            "Name": "漆黑蜻蜓"
                        },
                        {
                            "Value": "16",
                            "Name": "淺褐蜻蜓"
                        },
                        {
                            "Value": "17",
                            "Name": "善變蜻蜓"
                        },
                        {
                            "Value": "18",
                            "Name": "雙截蜻蜓"
                        },
                        {
                            "Value": "19",
                            "Name": "琥珀蜻蜓"
                        },
                        {
                            "Value": "20",
                            "Name": "喙鋏晏蜓"
                        },
                        {
                            "Value": "21",
                            "Name": "金黃蜻蜓"
                        },
                        {
                            "Value": "22",
                            "Name": "扶桑蜻蜓"
                        },
                        {
                            "Value": "23",
                            "Name": "呂宋蜻蜓"
                        },
                        {
                            "Value": "24",
                            "Name": "灰黑蜻蜓"
                        },
                        {
                            "Value": "25",
                            "Name": "霜白蜻蜓西里亞種"
                        },
                        {
                            "Value": "26",
                            "Name": "霜白蜻蜓中印亞種"
                        },
                        {
                            "Value": "27",
                            "Name": "杜松蜻蜓"
                        },
                        {
                            "Value": "28",
                            "Name": "赭黃蜻蜓"
                        },
                        {
                            "Value": "29",
                            "Name": "鼎脈蜻蜓"
                        },
                        {
                            "Value": "30",
                            "Name": "薄翅蜻蜓"
                        },
                        {
                            "Value": "31",
                            "Name": "溪神蜻蜓"
                        },
                        {
                            "Value": "32",
                            "Name": "黃紉蜻蜓"
                        },
                        {
                            "Value": "33",
                            "Name": "黑翅蜻蜓"
                        },
                        {
                            "Value": "34",
                            "Name": "藍黑蜻蜓"
                        },
                        {
                            "Value": "35",
                            "Name": "賽琳蜻蜓"
                        },
                        {
                            "Value": "36",
                            "Name": "三角蜻蜓"
                        },
                        {
                            "Value": "37",
                            "Name": "彩裳蜻蜓"
                        },
                        {
                            "Value": "38",
                            "Name": "赤衣蜻蜓"
                        },
                        {
                            "Value": "39",
                            "Name": "長尾蜻蜓"
                        },
                        {
                            "Value": "40",
                            "Name": "仲夏蜻蜓"
                        },
                        {
                            "Value": "41",
                            "Name": "秋紅蜻蜓"
                        },
                        {
                            "Value": "42",
                            "Name": "焰紅蜻蜓"
                        },
                        {
                            "Value": "43",
                            "Name": "紅脈蜻蜓"
                        },
                        {
                            "Value": "44",
                            "Name": "褐頂蜻蜓"
                        },
                        {
                            "Value": "45",
                            "Name": "孔凱蜻蜓"
                        },
                        {
                            "Value": "46",
                            "Name": "纖紅蜻蜓"
                        },
                        {
                            "Value": "47",
                            "Name": "黃基蜻蜓"
                        },
                        {
                            "Value": "48",
                            "Name": "夜遊蜻蜓"
                        },
                        {
                            "Value": "49",
                            "Name": "海霸蜻蜓微斑亞種"
                        },
                        {
                            "Value": "50",
                            "Name": "海霸蜻蜓粗斑亞種"
                        },
                        {
                            "Value": "51",
                            "Name": "大華蜻蜓"
                        },
                        {
                            "Value": "52",
                            "Name": "紫紅蜻蜓"
                        },
                        {
                            "Value": "53",
                            "Name": "樂仙蜻蜓"
                        },
                        {
                            "Value": "54",
                            "Name": "灰脈蜻蜓"
                        },
                        {
                            "Value": "55",
                            "Name": "褐基蜻蜓"
                        },
                        {
                            "Value": "56",
                            "Name": "高砂蜻蜓"
                        },
                        {
                            "Value": "57",
                            "Name": "灰影蜻蜓"
                        },
                        {
                            "Value": "58",
                            "Name": "纖腰蜻蜓"
                        }
                    ]
                }
            ]
        }
    ]
}